aldryn_wordpress_import/__init__.py
aldryn_wordpress_import/admin.py
aldryn_wordpress_import/factories.py
aldryn_wordpress_import/models.py
aldryn_wordpress_import/utils.py
aldryn_wordpress_import/management/__init__.py
aldryn_wordpress_import/management/commands/__init__.py
aldryn_wordpress_import/management/commands/wordpress_import.py
aldryn_wordpress_import/migrations/0001_initial.py
aldryn_wordpress_import/migrations/0002_auto__add_field_wordpressimport_create_authors__add_field_wordpressimp.py
aldryn_wordpress_import/migrations/__init__.py
aldryn_wordpress_import/templates/admin/aldryn_wordpress_import/wordpressimport/change_form.html
aldryn_wordpress_import-1.0b10.dist-info/DESCRIPTION.rst
aldryn_wordpress_import-1.0b10.dist-info/METADATA
aldryn_wordpress_import-1.0b10.dist-info/metadata.json
aldryn_wordpress_import-1.0b10.dist-info/RECORD
aldryn_wordpress_import-1.0b10.dist-info/top_level.txt
aldryn_wordpress_import-1.0b10.dist-info/WHEEL
