Metadata-Version: 2.0
Name: aldryn-wordpress-import
Version: 1.0b10
Summary: Wordpress import for aldryn-blog
Home-page: https://github.com/aldryn/aldryn-wordpress-import
Author: Divio AG
Author-email: info@divio.ch
License: LICENSE.txt
Platform: OS Independent
Classifier: Development Status :: 2 - Pre-Alpha
Classifier: Environment :: Web Environment
Classifier: Framework :: Django
Classifier: Intended Audience :: Developers
Classifier: License :: OSI Approved :: BSD License
Classifier: Operating System :: OS Independent
Classifier: Programming Language :: Python
Classifier: Topic :: Internet :: WWW/HTTP :: Dynamic Content
Classifier: Topic :: Software Development
Classifier: Topic :: Software Development :: Libraries :: Application Frameworks
Requires-Dist: Django (>=1.5.5)
Requires-Dist: aldryn-blog
Requires-Dist: BeautifulSoup
Requires-Dist: django-taggit
Requires-Dist: django-filer
Requires-Dist: lxml
Requires-Dist: python-dateutil
Requires-Dist: requests
